[
  {
    "idColuna": 1,
    "titulo": "Titulo",
    "descricao": "Uma descricao bem longa para um card de kanban",
    "info": "Rodapé do card, com uma informação extra"
  },
  {
    "idColuna": 1,
    "titulo": "Titulo",
    "descricao": "Uma descricao bem longa para um card de kanban",
    "info": "Rodapé do card, com uma informação extra"
  },
  {
    "idColuna": 1,
    "titulo": "Titulo",
    "descricao": "Uma descricao bem longa para um card de kanban",
    "info": "Rodapé do card, com uma informação extra"
  },
  {
    "idColuna": 2,
    "titulo": "Titulo",
    "descricao": "Uma descricao bem longa para um card de kanban",
    "info": "Rodapé do card, com uma informação extra"
  },
  {
    "idColuna": 2,
    "titulo": "Titulo",
    "descricao": "Uma descricao bem longa para um card de kanban",
    "info": "Rodapé do card, com uma informação extra"
  },
  {
    "idColuna": 2,
    "titulo": "Titulo",
    "descricao": "Uma descricao bem longa para um card de kanban",
    "info": "Rodapé do card, com uma informação extra"
  },
  {
    "idColuna": 3,
    "titulo": "Titulo",
    "descricao": "Uma descricao bem longa para um card de kanban",
    "info": "Rodapé do card, com uma informação extra"
  },
  {
    "idColuna": 3,
    "titulo": "Titulo",
    "descricao": "Uma descricao bem longa para um card de kanban",
    "info": "Rodapé do card, com uma informação extra"
  },
  {
    "idColuna": 3,
    "titulo": "Titulo",
    "descricao": "Uma descricao bem longa para um card de kanban",
    "info": "Rodapé do card, com uma informação extra"
  },
  {
    "idColuna": 4,
    "titulo": "Titulo",
    "descricao": "Uma descricao bem longa para um card de kanban",
    "info": "Rodapé do card, com uma informação extra"
  },
  {
    "idColuna": 4,
    "titulo": "Titulo",
    "descricao": "Uma descricao bem longa para um card de kanban",
    "info": "Rodapé do card, com uma informação extra"
  },
  {
    "idColuna": 4,
    "titulo": "Titulo",
    "descricao": "Uma descricao bem longa para um card de kanban",
    "info": "Rodapé do card, com uma informação extra"
  }
]
